Traffic_Light_Controller.v
`timescale 1ns / 1ps
//////////////////////////////////////////////////////////////////////////////////
// Company: 
// Engineer: 
// 
// Create Date: 16.07.2020 12:53:25
// Design Name: 
// Module Name: Traffic_Light_Controller
// Project Name: 
// Target Devices: 
// Tool Versions: 
// Description: 
// 
// Dependencies: 
// 
// Revision:
// Revision 0.01 - File Created
// Additional Comments:
// 
//////////////////////////////////////////////////////////////////////////////////


module Traffic_Light_Controller(


    input clk,rst,
    output reg [2:0]light_M1,
    output reg [2:0]light_S,
    output reg [2:0]light_MT,
    output reg [2:0]light_M2
    );
    
    parameter  S1=0, S2=1, S3 =2, S4=3, S5=4,S6=5;
    reg [3:0]count;
    reg[2:0] ps;
    parameter  sec7=7,sec5=5,sec2=2,sec3=3;

   
    
    always@(posedge clk or posedge rst)
        begin
        if(rst==1)
        begin
        ps<=S1;
        count<=0;
        end
        else
        
      
       
            
            case(ps)
                S1: if(count<sec7)
                        begin
                        ps<=S1;
                        count<=count+1;
                        end
                    else
                        begin
                        ps<=S2;
                        count<=0;
                        end
                S2: if(count<sec2)
                        begin
                        ps<=S2;
                        count<=count+1;
                        end

                    else
                        begin
                        ps<=S3;
                        count<=0;
                        end
                S3: if(count<sec5)
                        begin
                        ps<=S3;
                        count<=count+1;
                        end

                    else
                        begin
                        ps<=S4;
                        count<=0;
                        end
                S4:if(count<sec2)
                        begin
                        ps<=S4;
                        count<=count+1;
                        end

                    else
                        begin
                        ps<=S5;
                        count<=0;
                        end
                S5:if(count<sec3)
                        begin
                        ps<=S5;
                        count<=count+1;
                        end

                    else
                        begin
                        ps<=S6;
                        count<=0;
                        end

                S6:if(count<sec2)
                        begin
                        ps<=S6;
                        count<=count+1;
                        end

                    else
                        begin
                        ps<=S1;
                        count<=0;
                        end
                default: ps<=S1;
                endcase
            end   

            always@(ps)    
            begin
                
                case(ps)
                     
                    S1:
                    begin
                       light_M1<=3'b001;
                       light_M2<=3'b001;
                       light_MT<=3'b100;
                       light_S<=3'b100;
                    end
                    S2:
                    begin 
                       light_M1<=3'b001;
                       light_M2<=3'b010;
                       light_MT<=3'b100;
                       light_S<=3'b100;
                    end
                    S3:
                    begin
                       light_M1<=3'b001;
                       light_M2<=3'b100;
                       light_MT<=3'b001;
                       light_S<=3'b100;
                    end
                    S4:
                    begin
                       light_M1<=3'b010;
                       light_M2<=3'b100;
                       light_MT<=3'b010;
                       light_S<=3'b100;
                    end
                    S5:
                    begin
                       light_M1<=3'b100;
                       light_M2<=3'b100;
                       light_MT<=3'b100;
                       light_S<=3'b001;
                    end
                    S6:
                    begin 
                       light_M1<=3'b100;
                       light_M2<=3'b100;
                       light_MT<=3'b100;
                       light_S<=3'b010;
                    end
                    default:
                    begin 
                       light_M1<=3'b000;
                       light_M2<=3'b000;
                       light_MT<=3'b000;
                       light_S<=3'b000;
                    end
                    endcase
            end                
              

endmodule

module Traffic_Light_Controller_tb;
reg clk,rst;
wire [2:0]light_M1;
wire [2:0]light_S;
wire [2:0]light_MT;
wire [2:0]light_M2;
Traffic_Light_Controller dut(.clk(clk), .rst(rst), .light_M1(light_M1), .light_S(light_S), .light_MT(light_MT), .light_M2(light_M2));
initial 
    begin
        $dumpfile("Traffic_Light_Controller.vcd");
        $dumpvars(0,Traffic_Light_Controller_tb);
      clk=1'b0;
      forever #(10000000000/2) clk=~clk;
    end
initial 
begin
  rst=0;
  #10000000000;
  rst=1;
  #10000000000;
  rst=0;
  #(10000000000*200);
  $finish;  
end
endmodule

Traffic_Light_Controller.vcd
$date
	Mon Sep 13 21:26:34 2021
$end
$version
	Icarus Verilog
$end
$timescale
	1ps
$end
$scope module Traffic_Light_Controller_tb $end
$var wire 3 ! light_S [2:0] $end
$var wire 3 " light_MT [2:0] $end
$var wire 3 # light_M2 [2:0] $end
$var wire 3 $ light_M1 [2:0] $end
$var reg 1 % clk $end
$var reg 1 & rst $end
$scope module dut $end
$var wire 1 % clk $end
$var wire 1 & rst $end
$var reg 4 ' count [3:0] $end
$var reg 3 ( light_M1 [2:0] $end
$var reg 3 ) light_M2 [2:0] $end
$var reg 3 * light_MT [2:0] $end
$var reg 3 + light_S [2:0] $end
$var reg 3 , ps [2:0] $end
$upscope $end
$upscope $end
$enddefinitions $end
#0
$dumpvars
bx ,
bx +
bx *
bx )
bx (
bx '
0&
0%
bx $
bx #
bx "
bx !
$end
#5000000000000
b100 !
b100 +
b100 "
b100 *
b1 #
b1 )
b1 $
b1 (
b0 ,
1%
#10000000000000
b0 '
0%
1&
#15000000000000
1%
#20000000000000
0%
0&
#25000000000000
b1 '
1%
#30000000000000
0%
#35000000000000
b10 '
1%
#40000000000000
0%
#45000000000000
b11 '
1%
#50000000000000
0%
#55000000000000
b100 '
1%
#60000000000000
0%
#65000000000000
b101 '
1%
#70000000000000
0%
#75000000000000
b110 '
1%
#80000000000000
0%
#85000000000000
b111 '
1%
#90000000000000
0%
#95000000000000
b10 #
b10 )
b0 '
b1 ,
1%
#100000000000000
0%
#105000000000000
b1 '
1%
#110000000000000
0%
#115000000000000
b10 '
1%
#120000000000000
0%
#125000000000000
b1 "
b1 *
b100 #
b100 )
b0 '
b10 ,
1%
#130000000000000
0%
#135000000000000
b1 '
1%
#140000000000000
0%
#145000000000000
b10 '
1%
#150000000000000
0%
#155000000000000
b11 '
1%
#160000000000000
0%
#165000000000000
b100 '
1%
#170000000000000
0%
#175000000000000
b101 '
1%
#180000000000000
0%
#185000000000000
b10 "
b10 *
b10 $
b10 (
b0 '
b11 ,
1%
#190000000000000
0%
#195000000000000
b1 '
1%
#200000000000000
0%
#205000000000000
b10 '
1%
#210000000000000
0%
#215000000000000
b1 !
b1 +
b100 "
b100 *
b100 $
b100 (
b0 '
b100 ,
1%
#220000000000000
0%
#225000000000000
b1 '
1%
#230000000000000
0%
#235000000000000
b10 '
1%
#240000000000000
0%
#245000000000000
b11 '
1%
#250000000000000
0%
#255000000000000
b10 !
b10 +
b0 '
b101 ,
1%
#260000000000000
0%
#265000000000000
b1 '
1%
#270000000000000
0%
#275000000000000
b10 '
1%
#280000000000000
0%
#285000000000000
b100 !
b100 +
b1 #
b1 )
b1 $
b1 (
b0 '
b0 ,
1%
#290000000000000
0%
#295000000000000
b1 '
1%
#300000000000000
0%
#305000000000000
b10 '
1%
#310000000000000
0%
#315000000000000
b11 '
1%
#320000000000000
0%
#325000000000000
b100 '
1%
#330000000000000
0%
#335000000000000
b101 '
1%
#340000000000000
0%
#345000000000000
b110 '
1%
#350000000000000
0%
#355000000000000
b111 '
1%
#360000000000000
0%
#365000000000000
b10 #
b10 )
b0 '
b1 ,
1%
#370000000000000
0%
#375000000000000
b1 '
1%
#380000000000000
0%
#385000000000000
b10 '
1%
#390000000000000
0%
#395000000000000
b1 "
b1 *
b100 #
b100 )
b0 '
b10 ,
1%
#400000000000000
0%
#405000000000000
b1 '
1%
#410000000000000
0%
#415000000000000
b10 '
1%
#420000000000000
0%
#425000000000000
b11 '
1%
#430000000000000
0%
#435000000000000
b100 '
1%
#440000000000000
0%
#445000000000000
b101 '
1%
#450000000000000
0%
#455000000000000
b10 "
b10 *
b10 $
b10 (
b0 '
b11 ,
1%
#460000000000000
0%
#465000000000000
b1 '
1%
#470000000000000
0%
#475000000000000
b10 '
1%
#480000000000000
0%
#485000000000000
b1 !
b1 +
b100 "
b100 *
b100 $
b100 (
b0 '
b100 ,
1%
#490000000000000
0%
#495000000000000
b1 '
1%
#500000000000000
0%
#505000000000000
b10 '
1%
#510000000000000
0%
#515000000000000
b11 '
1%
#520000000000000
0%
#525000000000000
b10 !
b10 +
b0 '
b101 ,
1%
#530000000000000
0%
#535000000000000
b1 '
1%
#540000000000000
0%
#545000000000000
b10 '
1%
#550000000000000
0%
#555000000000000
b100 !
b100 +
b1 #
b1 )
b1 $
b1 (
b0 '
b0 ,
1%
#560000000000000
0%
#565000000000000
b1 '
1%
#570000000000000
0%
#575000000000000
b10 '
1%
#580000000000000
0%
#585000000000000
b11 '
1%
#590000000000000
0%
#595000000000000
b100 '
1%
#600000000000000
0%
#605000000000000
b101 '
1%
#610000000000000
0%
#615000000000000
b110 '
1%
#620000000000000
0%
#625000000000000
b111 '
1%
#630000000000000
0%
#635000000000000
b10 #
b10 )
b0 '
b1 ,
1%
#640000000000000
0%
#645000000000000
b1 '
1%
#650000000000000
0%
#655000000000000
b10 '
1%
#660000000000000
0%
#665000000000000
b1 "
b1 *
b100 #
b100 )
b0 '
b10 ,
1%
#670000000000000
0%
#675000000000000
b1 '
1%
#680000000000000
0%
#685000000000000
b10 '
1%
#690000000000000
0%
#695000000000000
b11 '
1%
#700000000000000
0%
#705000000000000
b100 '
1%
#710000000000000
0%
#715000000000000
b101 '
1%
#720000000000000
0%
#725000000000000
b10 "
b10 *
b10 $
b10 (
b0 '
b11 ,
1%
#730000000000000
0%
#735000000000000
b1 '
1%
#740000000000000
0%
#745000000000000
b10 '
1%
#750000000000000
0%
#755000000000000
b1 !
b1 +
b100 "
b100 *
b100 $
b100 (
b0 '
b100 ,
1%
#760000000000000
0%
#765000000000000
b1 '
1%
#770000000000000
0%
#775000000000000
b10 '
1%
#780000000000000
0%
#785000000000000
b11 '
1%
#790000000000000
0%
#795000000000000
b10 !
b10 +
b0 '
b101 ,
1%
#800000000000000
0%
#805000000000000
b1 '
1%
#810000000000000
0%
#815000000000000
b10 '
1%
#820000000000000
0%
#825000000000000
b100 !
b100 +
b1 #
b1 )
b1 $
b1 (
b0 '
b0 ,
1%
#830000000000000
0%
#835000000000000
b1 '
1%
#840000000000000
0%
#845000000000000
b10 '
1%
#850000000000000
0%
#855000000000000
b11 '
1%
#860000000000000
0%
#865000000000000
b100 '
1%
#870000000000000
0%
#875000000000000
b101 '
1%
#880000000000000
0%
#885000000000000
b110 '
1%
#890000000000000
0%
#895000000000000
b111 '
1%
#900000000000000
0%
#905000000000000
b10 #
b10 )
b0 '
b1 ,
1%
#910000000000000
0%
#915000000000000
b1 '
1%
#920000000000000
0%
#925000000000000
b10 '
1%
#930000000000000
0%
#935000000000000
b1 "
b1 *
b100 #
b100 )
b0 '
b10 ,
1%
#940000000000000
0%
#945000000000000
b1 '
1%
#950000000000000
0%
#955000000000000
b10 '
1%
#960000000000000
0%
#965000000000000
b11 '
1%
#970000000000000
0%
#975000000000000
b100 '
1%
#980000000000000
0%
#985000000000000
b101 '
1%
#990000000000000
0%
#995000000000000
b10 "
b10 *
b10 $
b10 (
b0 '
b11 ,
1%
#1000000000000000
0%
#1005000000000000
b1 '
1%
#1010000000000000
0%
#1015000000000000
b10 '
1%
#1020000000000000
0%
#1025000000000000
b1 !
b1 +
b100 "
b100 *
b100 $
b100 (
b0 '
b100 ,
1%
#1030000000000000
0%
#1035000000000000
b1 '
1%
#1040000000000000
0%
#1045000000000000
b10 '
1%
#1050000000000000
0%
#1055000000000000
b11 '
1%
#1060000000000000
0%
#1065000000000000
b10 !
b10 +
b0 '
b101 ,
1%
#1070000000000000
0%
#1075000000000000
b1 '
1%
#1080000000000000
0%
#1085000000000000
b10 '
1%
#1090000000000000
0%
#1095000000000000
b100 !
b100 +
b1 #
b1 )
b1 $
b1 (
b0 '
b0 ,
1%
#1100000000000000
0%
#1105000000000000
b1 '
1%
#1110000000000000
0%
#1115000000000000
b10 '
1%
#1120000000000000
0%
#1125000000000000
b11 '
1%
#1130000000000000
0%
#1135000000000000
b100 '
1%
#1140000000000000
0%
#1145000000000000
b101 '
1%
#1150000000000000
0%
#1155000000000000
b110 '
1%
#1160000000000000
0%
#1165000000000000
b111 '
1%
#1170000000000000
0%
#1175000000000000
b10 #
b10 )
b0 '
b1 ,
1%
#1180000000000000
0%
#1185000000000000
b1 '
1%
#1190000000000000
0%
#1195000000000000
b10 '
1%
#1200000000000000
0%
#1205000000000000
b1 "
b1 *
b100 #
b100 )
b0 '
b10 ,
1%
#1210000000000000
0%
#1215000000000000
b1 '
1%
#1220000000000000
0%
#1225000000000000
b10 '
1%
#1230000000000000
0%
#1235000000000000
b11 '
1%
#1240000000000000
0%
#1245000000000000
b100 '
1%
#1250000000000000
0%
#1255000000000000
b101 '
1%
#1260000000000000
0%
#1265000000000000
b10 "
b10 *
b10 $
b10 (
b0 '
b11 ,
1%
#1270000000000000
0%
#1275000000000000
b1 '
1%
#1280000000000000
0%
#1285000000000000
b10 '
1%
#1290000000000000
0%
#1295000000000000
b1 !
b1 +
b100 "
b100 *
b100 $
b100 (
b0 '
b100 ,
1%
#1300000000000000
0%
#1305000000000000
b1 '
1%
#1310000000000000
0%
#1315000000000000
b10 '
1%
#1320000000000000
0%
#1325000000000000
b11 '
1%
#1330000000000000
0%
#1335000000000000
b10 !
b10 +
b0 '
b101 ,
1%
#1340000000000000
0%
#1345000000000000
b1 '
1%
#1350000000000000
0%
#1355000000000000
b10 '
1%
#1360000000000000
0%
#1365000000000000
b100 !
b100 +
b1 #
b1 )
b1 $
b1 (
b0 '
b0 ,
1%
#1370000000000000
0%
#1375000000000000
b1 '
1%
#1380000000000000
0%
#1385000000000000
b10 '
1%
#1390000000000000
0%
#1395000000000000
b11 '
1%
#1400000000000000
0%
#1405000000000000
b100 '
1%
#1410000000000000
0%
#1415000000000000
b101 '
1%
#1420000000000000
0%
#1425000000000000
b110 '
1%
#1430000000000000
0%
#1435000000000000
b111 '
1%
#1440000000000000
0%
#1445000000000000
b10 #
b10 )
b0 '
b1 ,
1%
#1450000000000000
0%
#1455000000000000
b1 '
1%
#1460000000000000
0%
#1465000000000000
b10 '
1%
#1470000000000000
0%
#1475000000000000
b1 "
b1 *
b100 #
b100 )
b0 '
b10 ,
1%
#1480000000000000
0%
#1485000000000000
b1 '
1%
#1490000000000000
0%
#1495000000000000
b10 '
1%
#1500000000000000
0%
#1505000000000000
b11 '
1%
#1510000000000000
0%
#1515000000000000
b100 '
1%
#1520000000000000
0%
#1525000000000000
b101 '
1%
#1530000000000000
0%
#1535000000000000
b10 "
b10 *
b10 $
b10 (
b0 '
b11 ,
1%
#1540000000000000
0%
#1545000000000000
b1 '
1%
#1550000000000000
0%
#1555000000000000
b10 '
1%
#1560000000000000
0%
#1565000000000000
b1 !
b1 +
b100 "
b100 *
b100 $
b100 (
b0 '
b100 ,
1%
#1570000000000000
0%
#1575000000000000
b1 '
1%
#1580000000000000
0%
#1585000000000000
b10 '
1%
#1590000000000000
0%
#1595000000000000
b11 '
1%
#1600000000000000
0%
#1605000000000000
b10 !
b10 +
b0 '
b101 ,
1%
#1610000000000000
0%
#1615000000000000
b1 '
1%
#1620000000000000
0%
#1625000000000000
b10 '
1%
#1630000000000000
0%
#1635000000000000
b100 !
b100 +
b1 #
b1 )
b1 $
b1 (
b0 '
b0 ,
1%
#1640000000000000
0%
#1645000000000000
b1 '
1%
#1650000000000000
0%
#1655000000000000
b10 '
1%
#1660000000000000
0%
#1665000000000000
b11 '
1%
#1670000000000000
0%
#1675000000000000
b100 '
1%
#1680000000000000
0%
#1685000000000000
b101 '
1%
#1690000000000000
0%
#1695000000000000
b110 '
1%
#1700000000000000
0%
#1705000000000000
b111 '
1%
#1710000000000000
0%
#1715000000000000
b10 #
b10 )
b0 '
b1 ,
1%
#1720000000000000
0%
#1725000000000000
b1 '
1%
#1730000000000000
0%
#1735000000000000
b10 '
1%
#1740000000000000
0%
#1745000000000000
b1 "
b1 *
b100 #
b100 )
b0 '
b10 ,
1%
#1750000000000000
0%
#1755000000000000
b1 '
1%
#1760000000000000
0%
#1765000000000000
b10 '
1%
#1770000000000000
0%
#1775000000000000
b11 '
1%
#1780000000000000
0%
#1785000000000000
b100 '
1%
#1790000000000000
0%
#1795000000000000
b101 '
1%
#1800000000000000
0%
#1805000000000000
b10 "
b10 *
b10 $
b10 (
b0 '
b11 ,
1%
#1810000000000000
0%
#1815000000000000
b1 '
1%
#1820000000000000
0%
#1825000000000000
b10 '
1%
#1830000000000000
0%
#1835000000000000
b1 !
b1 +
b100 "
b100 *
b100 $
b100 (
b0 '
b100 ,
1%
#1840000000000000
0%
#1845000000000000
b1 '
1%
#1850000000000000
0%
#1855000000000000
b10 '
1%
#1860000000000000
0%
#1865000000000000
b11 '
1%
#1870000000000000
0%
#1875000000000000
b10 !
b10 +
b0 '
b101 ,
1%
#1880000000000000
0%
#1885000000000000
b1 '
1%
#1890000000000000
0%
#1895000000000000
b10 '
1%
#1900000000000000
0%
#1905000000000000
b100 !
b100 +
b1 #
b1 )
b1 $
b1 (
b0 '
b0 ,
1%
#1910000000000000
0%
#1915000000000000
b1 '
1%
#1920000000000000
0%
#1925000000000000
b10 '
1%
#1930000000000000
0%
#1935000000000000
b11 '
1%
#1940000000000000
0%
#1945000000000000
b100 '
1%
#1950000000000000
0%
#1955000000000000
b101 '
1%
#1960000000000000
0%
#1965000000000000
b110 '
1%
#1970000000000000
0%
#1975000000000000
b111 '
1%
#1980000000000000
0%
#1985000000000000
b10 #
b10 )
b0 '
b1 ,
1%
#1990000000000000
0%
#1995000000000000
b1 '
1%
#2000000000000000
0%
#2005000000000000
b10 '
1%
#2010000000000000
0%
#2015000000000000
b1 "
b1 *
b100 #
b100 )
b0 '
b10 ,
1%
